geoffrey_snakefood-0.0.1.dist-info/DESCRIPTION.rst
geoffrey_snakefood-0.0.1.dist-info/RECORD
geoffrey_snakefood-0.0.1.dist-info/WHEEL
geoffrey_snakefood-0.0.1.dist-info/top_level.txt
geoffrey_snakefood-0.0.1.dist-info/metadata.json
geoffrey_snakefood-0.0.1.dist-info/METADATA
geoffreyplugins/__init__.py
geoffreyplugins/snakefood.py
geoffreyplugins/snakefood/main.js
geoffreyplugins/snakefood/assets/.gitkeep
