Metadata-Version: 2.0
Name: geoffrey-snakefood
Version: 0.0.1
Summary: Python Dependency Graphs
Home-page: https://github.com/nilp0inter/geoffrey-snakefood
Author: Roberto Abdelkader Martínez Pérez
Author-email: robertomartinezp@gmail.com
License: UNKNOWN
Platform: UNKNOWN
